audioFX/Fx.py
audioFX/__init__.py
audioFX/config.toml
audioFX/example.py
audioFX-1.0.6.dist-info/LICENSE
audioFX-1.0.6.dist-info/METADATA
audioFX-1.0.6.dist-info/WHEEL
audioFX-1.0.6.dist-info/top_level.txt
audioFX-1.0.6.dist-info/RECORD
