Metadata-Version: 2.1
Name: audioFX
Version: 1.0.6
Summary: Audio effects library.
Author-email: Silvan Mertes <silvan.mertes@informatik.uni-augsburg.de>
License: MIT License        
Project-URL: Homepage, https://github.com/hcmlab/audio-fx
Keywords: audio,fx,flanger,distortion,tremolo,flanger,distortion,wahwah,chorus,pitch,griffin
Classifier: License :: OSI Approved :: MIT License
Classifier: Programming Language :: Python
Classifier: Programming Language :: Python :: 3
Requires-Python: >=3.5
License-File: LICENSE
Requires-Dist: librosa (>=0.9.2)
Requires-Dist: SoundFile (>=0.10.3.post1)
Requires-Dist: numpy
